polars_nightly-1.7.2.post20240919.dist-info/METADATA
polars_nightly-1.7.2.post20240919.dist-info/WHEEL
polars_nightly-1.7.2.post20240919.dist-info/licenses/LICENSE
polars/series/categorical.py
polars/series/binary.py
polars/series/list.py
polars/series/plotting.py
polars/series/series.py
polars/series/__init__.py
polars/series/utils.py
polars/series/string.py
polars/series/array.py
polars/series/datetime.py
polars/series/struct.py
polars/_utils/slice.py
polars/_utils/various.py
polars/_utils/cloud.py
polars/_utils/deprecation.py
polars/_utils/unstable.py
polars/_utils/convert.py
polars/_utils/parse/__init__.py
polars/_utils/parse/expr.py
polars/_utils/serde.py
polars/_utils/constants.py
polars/_utils/__init__.py
polars/_utils/getitem.py
polars/_utils/polars_version.py
polars/_utils/async_.py
polars/_utils/construction/dataframe.py
polars/_utils/construction/series.py
polars/_utils/construction/__init__.py
polars/_utils/construction/other.py
polars/_utils/construction/utils.py
polars/_utils/scan.py
polars/_utils/wrap.py
polars/_utils/udfs.py
polars/plugins.py
polars/dataframe/plotting.py
polars/dataframe/group_by.py
polars/dataframe/__init__.py
polars/dataframe/frame.py
polars/dataframe/_html.py
polars/config.py
polars/_typing.py
polars/type_aliases.py
polars/datatypes/constructor.py
polars/datatypes/convert.py
polars/datatypes/constants.py
polars/datatypes/__init__.py
polars/datatypes/_parse.py
polars/datatypes/group.py
polars/datatypes/classes.py
polars/datatypes/_utils.py
polars/io/plugins.py
polars/io/database/functions.py
polars/io/database/_cursor_proxies.py
polars/io/database/__init__.py
polars/io/database/_arrow_registry.py
polars/io/database/_executor.py
polars/io/database/_inference.py
polars/io/database/_utils.py
polars/io/pyarrow_dataset/functions.py
polars/io/pyarrow_dataset/__init__.py
polars/io/pyarrow_dataset/anonymous_scan.py
polars/io/avro.py
polars/io/spreadsheet/functions.py
polars/io/spreadsheet/_write_utils.py
polars/io/spreadsheet/__init__.py
polars/io/spreadsheet/_utils.py
polars/io/__init__.py
polars/io/ndjson.py
polars/io/json/__init__.py
polars/io/json/read.py
polars/io/iceberg.py
polars_nightly-1.7.2.post20240919.dist-info/RECORD
