Metadata-Version: 2.3
Name: polars-nightly
Version: 1.7.2.post20240919
Classifier: Development Status :: 5 - Production/Stable
Classifier: Environment :: Console
Classifier: Intended Audience :: Science/Research
Classifier: License :: OSI Approved :: MIT License
Classifier: Operating System :: OS Independent
Classifier: Programming Language :: Python
Classifier: Programming Language :: Python :: 3
Classifier: Programming Language :: Python :: 3 :: Only
Classifier: Programming Language :: Python :: 3.8
Classifier: Programming Language :: Python :: 3.9
Classifier: Programming Language :: Python :: 3.10
Classifier: Programming Language :: Python :: 3.11
Classifier: Programming Language :: Python :: 3.12
Classifier: Programming Language :: Rust
Classifier: Topic :: Scientific/Engineering
Requires-Dist: numpy >=1.16.0 ; extra == 'numpy'
Requires-Dist: pandas ; extra == 'pandas'
Requires-Dist: polars[pyarrow] ; extra == 'pandas'
Requires-Dist: pyarrow >=7.0.0 ; extra == 'pyarrow'
Requires-Dist: pydantic ; extra == 'pydantic'
Requires-Dist: fastexcel >=0.9 ; extra == 'calamine'
Requires-Dist: openpyxl >=3.0.0 ; extra == 'openpyxl'
Requires-Dist: xlsx2csv >=0.8.0 ; extra == 'xlsx2csv'
Requires-Dist: xlsxwriter ; extra == 'xlsxwriter'
Requires-Dist: polars[calamine,openpyxl,xlsx2csv,xlsxwriter] ; extra == 'excel'
Requires-Dist: adbc-driver-manager[dbapi] ; extra == 'adbc'
Requires-Dist: adbc-driver-sqlite[dbapi] ; extra == 'adbc'
Requires-Dist: connectorx >=0.3.2 ; extra == 'connectorx'
Requires-Dist: sqlalchemy ; extra == 'sqlalchemy'
Requires-Dist: polars[pandas] ; extra == 'sqlalchemy'
Requires-Dist: polars[adbc,connectorx,sqlalchemy] ; extra == 'database'
Requires-Dist: nest-asyncio ; extra == 'database'
Requires-Dist: fsspec ; extra == 'fsspec'
Requires-Dist: deltalake >=0.15.0 ; extra == 'deltalake'
Requires-Dist: pyiceberg >=0.5.0 ; extra == 'iceberg'
Requires-Dist: gevent ; extra == 'async'
Requires-Dist: cloudpickle ; extra == 'cloudpickle'
Requires-Dist: matplotlib ; extra == 'graph'
Requires-Dist: altair >=5.4.0 ; extra == 'plot'
Requires-Dist: great-tables >=0.8.0 ; extra == 'style'
Requires-Dist: backports-zoneinfo ; python_version < '3.9' and extra == 'timezone'
Requires-Dist: tzdata ; platform_system == 'Windows' and extra == 'timezone'
Requires-Dist: cudf-polars-cu12 ; extra == 'gpu'
Requires-Dist: polars[async,cloudpickle,database,deltalake,excel,fsspec,graph,iceberg,numpy,pandas,plot,pyarrow,pydantic,style,timezone] ; extra == 'all'
Provides-Extra: numpy
Provides-Extra: pandas
Provides-Extra: pyarrow
Provides-Extra: pydantic
Provides-Extra: calamine
Provides-Extra: openpyxl
Provides-Extra: xlsx2csv
Provides-Extra: xlsxwriter
Provides-Extra: excel
Provides-Extra: adbc
Provides-Extra: connectorx
Provides-Extra: sqlalchemy
Provides-Extra: database
Provides-Extra: fsspec
Provides-Extra: deltalake
Provides-Extra: iceberg
Provides-Extra: async
Provides-Extra: cloudpickle
Provides-Extra: graph
Provides-Extra: plot
Provides-Extra: style
Provides-Extra: timezone
Provides-Extra: gpu
Provides-Extra: all
License-File: LICENSE
Summary: Blazingly fast DataFrame library
Keywords: dataframe,arrow,out-of-core
Author-email: Ritchie Vink <ritchie46@gmail.com>
Requires-Python: >=3.8
Project-URL: Homepage, https://www.pola.rs/
Project-URL: Documentation, https://docs.pola.rs/api/python/stable/reference/index.html
Project-URL: Repository, https://github.com/pola-rs/polars
Project-URL: Changelog, https://github.com/pola-rs/polars/releases
